[{"name":"yellow color","source":"\\[yellow\\]","flags":"g","replace":"<span style=\"color:gold\">","active":true,"filterlinks":false},{"name":"pink color","source":"\\[pink\\]","flags":"g","replace":"<span style=\"color:#FFBBFF\">","active":true,"filterlinks":false},{"name":"violet color","source":"\\[violet\\]","flags":"g","replace":"<span style=\"color:#660099\">","active":true,"filterlinks":false},{"name":"brown color","source":"\\[brown\\]","flags":"g","replace":"<span style=\"color:#660000\">","active":true,"filterlinks":false},{"name":"white color on black","source":"\\[bw\\]","flags":"g","replace":"<span style=\"color:white; background-color:black\">","active":true,"filterlinks":false},{"name":"yusaku","source":"\\[yu\\]","flags":"gi","replace":"<span style=\"font-size:20px;color:#FFFFFF; font-family:HG創英角ﾎﾟｯﾌﾟ体,sans-serif;text-shadow:0px 0px 4px #000000,0px 0px 4px #000000,0px 0px 4px #000000\">","active":true,"filterlinks":false},{"name":"Ohasaku","source":"\\[an\\]","flags":"gi","replace":"<span style=\"font-size:24px;color:#18E0FF; font-family:Fuwafude,sans-serif;text-shadow:3px 3px 1px #000000,-3px 3px 1px #000000,3px -3px 1px #000000,-3px -3px 1px #000000,3px 0px 1px #000000,0px 3px 1px #000000,-3px 0px 1px #000000,0px -3px 1px #000000\">","active":true,"filterlinks":false},{"name":"distinguished text","source":"\\[d\\]","flags":"g","replace":"<span class=\"dist\">","active":true,"filterlinks":false},{"name":"fire text","source":"\\[f\\]","flags":"g","replace":"<span style=\"color:#FFFFFF;padding-top:20px; text-shadow:0px 0px 4px #000000, 0px -5px 4px #FFFF33, 2px -8px 6px #FFDD33, -2px -15px 10px #FF8800, 2px -20px 18px #FF2200; letter-spacing:2px\">","active":true,"filterlinks":false},{"name":"hirogaru","source":"\\[hirogaru\\]","flags":"g","replace":"<span style=\"letter-spacing: 30pt\">","active":true,"filterlinks":false},{"name":"okina","source":"\\[okina\\]","flags":"gi","replace":"<span class=\"cardboardokina\">","active":true,"filterlinks":false},{"name":"hibanafont","source":"\\[hibana\\]","flags":"gi","replace":"<span class=\"hibanalyrics\">","active":true,"filterlinks":false},{"name":"closing font style","source":"\\[\\/\\]","flags":"g","replace":"</span>","active":true,"filterlinks":false},{"name":"scroll","source":"\\[scroll\\]\\s?(\\S*(?:\\s+\\S+)*)","flags":"g","replace":"<marquee> \\1 </marquee>","active":true,"filterlinks":false},{"name":"scrollsuperspeed","source":"\\[scroll200\\]\\s?(\\S*(?:\\s+\\S+)*)","flags":"g","replace":"<marquee scrollamount=\"200\"> \\1 </marquee>","active":true,"filterlinks":false},{"name":"rscroll","source":"\\[rscroll\\]\\s?(\\S*(?:\\s+\\S+)*)","flags":"g","replace":"<marquee direction=\"right\"> \\1 </marquee>","active":true,"filterlinks":false},{"name":"rscroll200","source":"\\[rscroll200\\]\\s?(\\S*(?:\\s+\\S+)*)","flags":"g","replace":"<marquee direction=\"right\" scrollamount=\"200\"> \\1 </marquee>","active":true,"filterlinks":false},{"name":"blur","source":"\\[bl\\]\\s?(\\S*(?:\\s+\\S+)*)","flags":"g","replace":"<span style=\"filter:blur(1.5px) contrast(50%)\"> \\1 </span>","active":true,"filterlinks":false},{"name":"blink","source":"\\[blink\\]\\s?(\\S*(?:\\s+\\S+)*)","flags":"g","replace":"<span class=\"blink\"> \\1 </span>","active":true,"filterlinks":false},{"name":"bright","source":"\\[br\\]\\s?(\\S*(?:\\s+\\S+)*)","flags":"g","replace":"<span style=\"filter:brightness(200%) drop-shadow(0 0 5px #fff)\"> \\1 </span>","active":true,"filterlinks":false},{"name":"grayscale","source":"\\[gs\\]\\s?(\\S*(?:\\s+\\S+)*)","flags":"g","replace":"<span class=\"grayscale\"> \\1 </span>","active":true,"filterlinks":false},{"name":"hue","source":"\\[hue\\]\\s?(\\S*(?:\\s+\\S+)*)","flags":"g","replace":"<span class=\"hueanim\"> \\1 </span>","active":true,"filterlinks":false},{"name":"inv","source":"\\[inv\\]\\s?(\\S*(?:\\s+\\S+)*)","flags":"g","replace":"<span class=\"invert\"> \\1 </span>","active":true,"filterlinks":false},{"name":"opa","source":"\\[opa\\]\\s?((?:\\S*\\s?)+)","flags":"g","replace":"<span style=\"opacity:.25\"> \\1 </span>","active":true,"filterlinks":false},{"name":"usagi","source":"\\[usagi\\]\\s?(\\S*(?:\\s+\\S+)*)","flags":"g","replace":"<span class=\"pyonpyon\"> \\1 </marquee>","active":true,"filterlinks":false},{"name":"viblate","source":"\\[vib\\]\\s?(\\S*(?:\\s+\\S+)*)","flags":"g","replace":"<span class=\"vib\"> \\1 </span>","active":true,"filterlinks":false},{"name":"Yaxisrot","source":"\\[yax\\]\\s?(\\S*(?:\\s+\\S+)*)","flags":"g","replace":"<span class=\"Yaxisrot\"> \\1 </span>","active":true,"filterlinks":false},{"name":"yoko","source":"\\[yoko\\]\\s?(\\S*(?:\\s+\\S+)*)","flags":"g","replace":"<span class=\"m_mark_yoko\"> \\1 </span>","active":true,"filterlinks":false},{"name":"yura","source":"\\[yura\\]\\s?(\\S*(?:\\s+\\S+)*)","flags":"g","replace":"<span class=\"yura\"> \\1 </span>","active":true,"filterlinks":false},{"name":"marquee alternate10","source":"\\[round\\]\\s?(\\S*(?:\\s+\\S+)*)","flags":"g","replace":"<marquee scrollamount=\"10\" behavior=\"alternate\"> \\1 </marquee>","active":true,"filterlinks":false},{"name":"marquee alternate5","source":"\\[round0\\]\\s?(\\S*(?:\\s+\\S+)*)","flags":"g","replace":"<marquee scrollamount=\"5\" behavior=\"alternate\"> \\1 </marquee>","active":true,"filterlinks":false},{"name":"marquee alternate20","source":"\\[round1\\]\\s?(\\S*(?:\\s+\\S+)*)","flags":"g","replace":"<marquee scrollamount=\"20\" behavior=\"alternate\"> \\1 </marquee>","active":true,"filterlinks":false},{"name":"mirror","source":"(^|\\s)@([\\w\\-]+(?:\\d+_)?\\d{3}[\\w\\-]*)","flags":"g","replace":"\\1<span style=\"display:inline-block;transform:rotateY(180deg)\"> \\2 </span>","active":true,"filterlinks":false},{"name":"rotz","source":"(^|\\s)z\\!([\\w\\-]+(?:\\d+_)?\\d{3}[\\w\\-]*)","flags":"g","replace":"\\1<span class=\"rotz\"> \\2 </span>","active":true,"filterlinks":false},{"name":"raise","source":"(^|\\s)r\\!([\\w\\-]+(?:\\d+_)?\\d{3}[\\w\\-]*)","flags":"g","replace":"\\1<span class=\"raise\"> \\2 </span>","active":true,"filterlinks":false},{"name":"AYURA!","source":"(^|\\s)a\\!([\\w\\-]+(?:\\d+_)?\\d{3}[\\w\\-]*)","flags":"g","replace":"\\1<span class=\"ayura\"> \\2 </span>","active":true,"filterlinks":false},{"name":"Y!","source":"(^|\\s)Y\\!([\\w\\-]+(?:\\d+_)?\\d{3}[\\w\\-]*)","flags":"g","replace":"\\1<span class=\"yura btcn\"> \\2 </span>","active":true,"filterlinks":false},{"name":"macedonia","source":"(^|\\s)\\!\\!([\\w\\-]+(?:\\d+_)?\\d{3}[\\w\\-]*)","flags":"g","replace":"\\1<span class=\"macedonia\"> \\2 </span>","active":true,"filterlinks":false},{"name":"BB","source":"(^|\\s)b\\!([\\w\\-]+(?:\\d+_)?\\d{3}[\\w\\-]*)","flags":"g","replace":"\\1<span class=\"bb\"> \\2 </span>","active":true,"filterlinks":false},{"name":"god","source":"(^|\\s)g\\!([\\w\\-]+(?:\\d+_)?\\d{3}[\\w\\-]*)","flags":"g","replace":"\\1<span class=\"god-knows\"> \\2 </span>","active":true,"filterlinks":false},{"name":"hibana","source":"^h\\!([\\w\\-]+(?:\\d+_)?\\d{3}[\\w\\-]*)$","flags":"g","replace":"<span class=\"hibw\"><span class=\"hibimg\"> \\1 </span><span class=\"hibret\"></span></span>","active":true,"filterlinks":false},{"name":"telecas","source":"^t\\!([\\w\\-]+(?:\\d+_)?\\d{3}[\\w\\-]*)$","flags":"g","replace":"<span class=\"telecas\"> \\1 </span>","active":true,"filterlinks":false},{"name":"bitter","source":"^B\\!(@?[\\w\\-]+(?:\\d+_)?\\d{3}[\\w\\-]*)$","flags":"g","replace":"<span class=\"bitter-super\"><span class=\"bitter-wrapper\"><span class=\"bitter-emote\"> \\1 </span><span class=\"bitter-choco\"><span>ビ</span><span>タ</span><span>ー</span><span>チ</span><span>ョ</span><span>コ</span><span>デ</span><span>コ</span><span>レ</span><span>ー</span><span>シ</span><span>ョ</span><span>ン</span></span></span></span>","active":true,"filterlinks":false},{"name":"inabakumori","source":"^l\\!([\\w\\-]+(?:\\d+_)?\\d{3}[\\w\\-]*)$","flags":"g","replace":"<span class=\"loopw\"><span class=\"loopspinner grayscale\"> \\1 </span><span class=\"loopl\">ループスピナ</span></span>","active":true,"filterlinks":false},{"name":"NayutailieN","source":"(^|\\s)n\\!([\\w\\-]+(?:\\d+_)?\\d{3}[\\w\\-]*)$","flags":"g","replace":"\\1<span class=\"nytn\"> \\2 </span>","active":true,"filterlinks":false},{"name":"NayutailieN2","source":"(^|\\s)n(\\d+)\\!([\\w\\-]+(?:\\d+_)?\\d{3}[\\w\\-]*)","flags":"g","replace":"\\1<span style=\"display:inline-block;animation:nytn calc(60s/\\2*2) step-end infinite\"> \\3 </span>","active":true,"filterlinks":false},{"name":"CARDBOARD OKINA","source":"\\[okn\\](.+?)\\[\\/okn\\]","flags":"g","replace":"<span class=\"cardboardokina\">\\1</span>","active":true,"filterlinks":false},{"name":"Charle - 0pacity","source":"\\[0\\](.+?)\\[\\/0\\]","flags":"g","replace":"<span style=\"opacity:0\">\\1</span>","active":true,"filterlinks":false},{"name":"Charle - wetcheek","source":"\\[w\\](.+?)\\[\\/w\\]","flags":"g","replace":"<span class=\"char-wetcheek\">\\1</span>","active":true,"filterlinks":false},{"name":"Charle - nightherd","source":"\\[n\\](.+?)\\[\\/n\\]","flags":"g","replace":"<span class=\"char-nightherd\">\\1</span>","active":true,"filterlinks":false},{"name":"Charle - collapse","source":"\\[col\\](.+?)\\[\\/col\\]","flags":"g","replace":"<span class=\"char-collapse\">\\1</span>","active":true,"filterlinks":false},{"name":"Charle - Speedcol","source":"\\[sc\\](.+?)\\[\\/sc\\]","flags":"g","replace":"<span class=\"char-speedcol\">\\1</span>","active":true,"filterlinks":false},{"name":"Charle - slowcol","source":"\\[slc\\](.+?)\\[\\/slc\\]","flags":"g","replace":"<span class=\"char-slowcol\"> \\1 </span>","active":true,"filterlinks":false},{"name":"hatelife","source":"\\[h\\](.+?)\\[\\/h\\]","flags":"g","replace":"<span class=\"hatelife\">\\1</span>","active":true,"filterlinks":false},{"name":"hatelife_medium","source":"\\[hm\\](.{0,2})\\[\\/hm\\]","flags":"g","replace":"<span class=\"hatelife yaya_bigg\">\\1</span>","active":true,"filterlinks":false},{"name":"hatelife-big","source":"\\[hb\\](.{0,2})\\[\\/hb\\]","flags":"g","replace":"<span class=\"hatelife bigg\">\\1</span>","active":true,"filterlinks":false},{"name":"hatelife-position","source":"\\[pos([0-9]|10)\\](.+?)\\[\\/pos\\]","flags":"g","replace":"<span class=\"hateposition\\1\">\\2</span>","active":true,"filterlinks":false},{"name":"hibanalyrics","source":"\\[hib\\](.+?)\\[\\/hib\\]","flags":"g","replace":"<span class=\"hibanalyrics\">\\1</span>","active":true,"filterlinks":false},{"name":"PANDA HERO","source":"\\[pdhr\\](.{0,2})\\[\\/pdhr\\]","flags":"g","replace":"<span class=\"hibanalyrics bigg\">\\1</span>","active":true,"filterlinks":false},{"name":"Charles","source":"\\[char\\](.+?)\\[\\/char\\]","flags":"g","replace":"<span class=\"char hibanalyrics\">\\1</span>","active":true,"filterlinks":false},{"name":"girl-autopsy","source":"\\[gap\\](.+?)\\[\\/gap\\]","flags":"g","replace":"<span class=\"girl-autopsy\"><span class=\"girl-autopsy-contents\">\\1</span></span>","active":true,"filterlinks":false},{"name":"test","source":"\\S*anonfiles\\S*","flags":"g","replace":"クッキー☆","active":true,"filterlinks":false},{"name":"ck","source":"^!ck\\s(\\S+)$","flags":"g","replace":"<a href=\"https://w.atwiki.jp/cookie_kaisetu/?cmd=wikisearch&keyword=\\1&andor=and\" target=\"_blank\" rel=\"noopener noreferrer\">解説wikiから\"\\1\"の検索結果</a>","active":true,"filterlinks":false},{"name":"mk","source":"^!mk\\s(\\S+)$","flags":"g","replace":"<a href=\"https://wikiwiki.jp/marius/?cmd=search&word=\\1&type=AND\" target=\"_blank\" rel=\"noopener noreferrer\">マリwikiから\"\\1\"の検索結果</a>","active":true,"filterlinks":false},{"name":"jk","source":"^!jk\\s(\\S+)$","flags":"g","replace":"<a href=\"https://wikiwiki.jp/9720246/?cmd=search&word=\\1&type=AND\" target=\"_blank\" rel=\"noopener noreferrer\">ク実wikiから\"\\1\"の検索結果</a>","active":true,"filterlinks":false},{"name":"2k","source":"^!2k\\s(\\S+)$","flags":"g","replace":"<a href=\"https://wikiwiki.jp/cookie2/?cmd=search&word=\\1&type=AND\" target=\"_blank\" rel=\"noopener noreferrer\">2代目wikiから\"\\1\"の検索結果</a>","active":true,"filterlinks":false},{"name":"MADチェック！","source":"(^|\\s)MADチェック！(?!\\S)","flags":"gi","replace":"\\1YNT001madstamp","active":true,"filterlinks":false},{"name":"kawaiiSIK","source":"(^|\\s)kawaii(?!\\S)","flags":"gi","replace":"\\1YMN108SIKstamp","active":true,"filterlinks":false},{"name":"manzokuka","source":"(^|\\s)manzokuka\\?(?!\\S)","flags":"gi","replace":"\\1kioku073mariusmanzokuka?-stamp","active":true,"filterlinks":false},{"name":"tasukaru","source":"(^|\\s)tasukaru(?!\\S)","flags":"gi","replace":"\\1PCLY002 PCLY003","active":true,"filterlinks":false},{"name":"fuckadmin","source":"(^|\\s)fu?c?kadmin(?!\\S)","flags":"gi","replace":"\\1HIKNKU002admin","active":true,"filterlinks":false},{"name":"carry","source":"(^|\\s)carry(?!\\S)","flags":"gi","replace":"\\1kanna015","active":true,"filterlinks":false},{"name":"sore","source":"(^|\\s)sore(?!\\S)","flags":"gi","replace":"\\1arinu002akiminoriko","active":true,"filterlinks":false},{"name":"skmdy","source":"(^|\\s)skmdy\\!?(?!\\S)","flags":"gi","replace":"\\1PCLY001skmdy","active":true,"filterlinks":false},{"name":"ok","source":"^ok$","flags":"g","replace":"M-1_002TWstamp","active":true,"filterlinks":false},{"name":"ore","source":"(^|\\s)ore(?!\\S)","flags":"gi","replace":"\\1MKNSN009moji_ore","active":true,"filterlinks":false},{"name":"ukeirenasai","source":"(^|\\s)ukeirenasai(?!\\S)","flags":"gi","replace":"\\1ALISON005KGYmoji","active":true,"filterlinks":false},{"name":"ukeireru","source":"(^|\\s)ukeireru(?!\\S)","flags":"gi","replace":"\\1ALISON006EIRNmoji","active":true,"filterlinks":false},{"name":"yurusenai","source":"(^|\\s)yurusenai(?!\\S)","flags":"gi","replace":"\\1kosayu005moji_yurusenai","active":true,"filterlinks":false},{"name":"rix_combo","source":"(^|\\s)combo(?!\\S)","flags":"gi","replace":"\\1combo001moji","active":true,"filterlinks":false},{"name":"rix_kora-","source":"(^|\\s)kora-!*(?!\\S)","flags":"gi","replace":"\\1moji026kora-!!","active":true,"filterlinks":false},{"name":"rix_fukai","source":"(^|\\s)(?:f|h)ukai(?!\\S)","flags":"gi","replace":"\\1TKTKKMCe018moji_fukai","active":true,"filterlinks":false},{"name":"rix_MGR","source":"(^|\\s)mgr(?!\\S)","flags":"gi","replace":"\\1MGR002full","active":true,"filterlinks":false},{"name":"rix_yurusanae","source":"(^|\\s)(?:yurusanae|yrsne)(?!\\S)","flags":"gi","replace":"\\1yurusanae001","active":true,"filterlinks":false},{"name":"rix_yuuhei","source":"(^|\\s)yu{1,2}hei(?!\\S)","flags":"gi","replace":"\\1yuuhei002","active":true,"filterlinks":false},{"name":"rix_zuriaya","source":"(^|\\s)(?:zuriaya|zray)(?!\\S)","flags":"gi","replace":"\\1zuriaya001ero","active":true,"filterlinks":false},{"name":"bakuha","source":"(^|\\s)bakuha(?!\\S)","flags":"gi","replace":"\\1bakuha001","active":true,"filterlinks":false},{"name":"emotefire","source":"(^|\\s)fire(?!\\S)","flags":"gi","replace":"\\1effect001fire","active":true,"filterlinks":false},{"name":"emotesmoke","source":"(^|\\s)smoke(?!\\S)","flags":"gi","replace":"\\1effect002smoke","active":true,"filterlinks":false},{"name":"emoteblood","source":"(^|\\s)blood(?!\\S)","flags":"gi","replace":"\\1effect003blood","active":true,"filterlinks":false},{"name":"kuro","source":"(^|\\s)kuro(?!\\S)","flags":"gi","replace":"\\1M-1_198kuro","active":true,"filterlinks":false},{"name":"shiro","source":"(^|\\s)(shiro|siro)(?!\\S)","flags":"gi","replace":"\\1M-1_199shiro","active":true,"filterlinks":false},{"name":"aka","source":"(^|\\s)aka(?!\\S)","flags":"gi","replace":"\\1M-1_200aka","active":true,"filterlinks":false},{"name":"zisatu","source":"(^|\\s)(?:z|j)isats?u(?!\\S)","flags":"gi","replace":"\\1MIMI008spieca","active":true,"filterlinks":false},{"name":"deriketu","source":"(^|\\s)derikets?u(?!\\S)","flags":"gi","replace":"\\1derisakura002ketsu","active":true,"filterlinks":false},{"name":"ataname","source":"(^|\\s)ataname(?!\\S)","flags":"gi","replace":"\\1mangekyou005CRN001ataname","active":true,"filterlinks":false},{"name":"atuize","source":"(^|\\s)ats?uize(?!\\S)","flags":"gi","replace":"\\1atuize001","active":true,"filterlinks":false},{"name":"cool","source":"(^|\\s)cool(?!\\S)","flags":"gi","replace":"\\1coolchoice001","active":true,"filterlinks":false},{"name":"dereaya","source":"(^|\\s)(dereaya|dray)(?!\\S)","flags":"gi","replace":"\\1ALCdere001AY","active":true,"filterlinks":false},{"name":"dorodoro","source":"(^|\\s)namaenonai(?:j|z)in(?:j|z)y?anoyabe-yats?u(?!\\S)","flags":"g","replace":"\\1hifurin013dorodoro","active":true,"filterlinks":false},{"name":"hage","source":"(^|\\s)hage(?!\\S)","flags":"gi","replace":"\\1higashiyama001hage","active":true,"filterlinks":false},{"name":"horahora514","source":"(^|\\s)horahora514(?!\\S)","flags":"gi","replace":"\\1KIS001horahora","active":true,"filterlinks":false},{"name":"kaeyo","source":"(^|\\s)kaeyo(?!\\S)","flags":"gi","replace":"\\1akahama001kaeyo","active":true,"filterlinks":false},{"name":"kansou!","source":"(^|\\s)kan{1,2}sou(?!\\S)","flags":"gi","replace":"\\1moji022kansou!","active":true,"filterlinks":false},{"name":"kugyou","source":"(^|\\s)kugyou(?!\\S)","flags":"gi","replace":"\\1kugyou003","active":true,"filterlinks":false},{"name":"night","source":"(^|\\s):night(?!\\S)","flags":"gi","replace":"\\1easter001night","active":true,"filterlinks":false},{"name":"nayuta","source":"(^|\\s)nayuta(?!\\S)","flags":"gi","replace":"\\1M-1_053HJR100nayutastamp","active":true,"filterlinks":false},{"name":"VS","source":"(^|\\s)VS(?!\\S)","flags":"gi","replace":"\\1moji079VS ","active":true,"filterlinks":false},{"name":"kasen","source":"(^|\\s)kasen(?!\\S)","flags":"gi","replace":"<span class=\"kasen\"> M-1_160KSN </span>","active":true,"filterlinks":false},{"name":"あｓｄｆ","source":"(^|\\s)(?:[あa][ｓs][ｄd][ｆf])(?!\\S)","flags":"gi","replace":"\\1M-1_074YSKstamp","active":true,"filterlinks":false},{"name":"a","source":"^a$","flags":"g","replace":"あーまわってー三(‘ω’)三( ε: )三(.ω.)三( :3 )三(‘ω’)三( ε: )三(.ω.)三( :3 )ｺﾞﾛｺﾞﾛｺﾞﾛ","active":true,"filterlinks":false},{"name":"c","source":"^c$","flags":"g","replace":"ちょｗそれヤジュセンのパイセン便乗ファッシャスのおいKMRァ～ﾎﾟｯﾁｬﾏのタマもホラ舐めて 乳首感じるオォンが入ってないやん（小並ｗのおっさんが出るイキ顔さねえからなぁ～（クボタイｗ","active":true,"filterlinks":false},{"name":"e","source":"^e$","flags":"g","replace":"(ﾟ∀ﾟ)o彡゜えーりん！えーりん！","active":true,"filterlinks":false},{"name":"f","source":"^f$","flags":"g","replace":"フシギィ…！ ココロォ…！ ココロォ…！ フシギィ…！","active":true,"filterlinks":false},{"name":"g","source":"^g$","flags":"g","replace":"＼（罪）／　ｹﾞﾝｹﾞﾝｹﾞﾖﾖﾝ　ｹﾞﾖｹﾞﾖｹﾞｹﾞﾝ　＼（罪）／","active":true,"filterlinks":false},{"name":"i","source":"^i$","flags":"g","replace":"イヒーヒヒヒヒwwwwマ゛マ゛ーーーーーーー！！！オギャwwwwwwあばばばばばばwwwwマッマーーーー！！！ワンワンwwニャンニャンwwwwウア゛ーーーーーーー！！！","active":true,"filterlinks":false},{"name":"k","source":"^k$","flags":"g","replace":"金曜日恒例の乳首つねりいっとく？ ??","active":true,"filterlinks":false},{"name":"n","source":"^n$","flags":"g","replace":"NYNKRN001myorenji ぅえーっと、携帯からの投稿なので、サビしか歌えませんが...時間的な問題で！えーっと、「恋愛勇者」サビ、歌いたいと思います。じゃあいきます視線があってそーのきになってそしたらクレイジー止まらぬいぇ～フラグ作って端から折ってわずか３日で思い敗れてぇかよわいもんでだ（呼吸）いぶ凹んで５日寝込んで次の区いぇ～突っ走って道誤っていくらなんでも勇者すぎ～る～さ～思考回路～を～うた～が～え～んえーと、下手なんですけど聴いてくれてありがとうございました　では！","active":true,"filterlinks":false},{"name":"N","source":"^N$","flags":"g","replace":"NYNKRN001myorenji 多々良小傘役をやらせてもらいました。にゃんころねです。ぅえっとですね、今回かわいい小傘ちゃんをやらせて頂いて、ほんと楽しかったです。えーと、みんないい演技だったと思うので、何回でもこれ聞いてあげてください。はい、よろしくお願いします。ではありがとうございました。","active":true,"filterlinks":false},{"name":"r","source":"^r$","flags":"g","replace":"リング・スズネたんのフレンチ・クルーラーをムシャムシャしたい(*'ω'*)","active":true,"filterlinks":false},{"name":"s","source":"^s$","flags":"g","replace":"＼(・ω・＼)SAN値！(／・ω・)／ピンチ！","active":true,"filterlinks":false},{"name":"u","source":"^u$","flags":"g","replace":"(」・ω・)」うー！(／・ω・)／にゃー！","active":true,"filterlinks":false},{"name":"U","source":"^U$","flags":"g","replace":"ウン恋曲:星野源営みの街が暮れたらウ ン コ 出 すﾌﾞﾂﾌﾞﾁﾁﾁﾌﾞﾘﾘｯﾌﾞｩｩｩｩｯｯ！！！！くっっっっっっっっさイクイクイクイクイクイクイクイクイクイクイクイクイクイクイクイクイク","active":true,"filterlinks":false},{"name":"umauma","source":"^ウ$","flags":"g","replace":"ｳｯｰｳｯｰｳﾏｳﾏ(ﾟ∀ﾟ)","active":true,"filterlinks":false},{"name":"gyate1","source":"gyate1","flags":"g","replace":"呪即説呪曰！","active":true,"filterlinks":false},{"name":"gyate2","source":"gyate2","flags":"g","replace":"掲諦掲諦！","active":true,"filterlinks":false},{"name":"gyate3","source":"gyate3","flags":"g","replace":"波羅掲諦！","active":true,"filterlinks":false},{"name":"gyate4","source":"gyate4","flags":"g","replace":"波羅僧掲諦！","active":true,"filterlinks":false},{"name":"gyate5","source":"gyate5","flags":"g","replace":"菩提薩婆賀！","active":true,"filterlinks":false},{"name":"gyate6","source":"gyate6","flags":"g","replace":"般若心経！","active":true,"filterlinks":false},{"name":"warabe0","source":"^warabe0$","flags":"g","replace":"童祭 ? for Wedding","active":true,"filterlinks":false},{"name":"warabe1","source":"^warabe1$","flags":"g","replace":"ありがとう　ありがとう","active":true,"filterlinks":false},{"name":"warabe2","source":"^warabe2$","flags":"g","replace":"博（ひろ）く麗しい人間と","active":true,"filterlinks":false},{"name":"warabe3","source":"^warabe3$","flags":"g","replace":"妖怪の物語から","active":true,"filterlinks":false},{"name":"warabe4","source":"^warabe4$","flags":"g","replace":"ゆめを?","active":true,"filterlinks":false},{"name":"warabe5","source":"^warabe5$","flags":"g","replace":"あなたが教えてくれた幻想は","active":true,"filterlinks":false},{"name":"warabe6","source":"^warabe6$","flags":"g","replace":"私達の心で輝いた","active":true,"filterlinks":false},{"name":"warabe7","source":"^warabe7$","flags":"g","replace":"おめでとう　おめでとう","active":true,"filterlinks":false},{"name":"warabe8","source":"^warabe8$","flags":"g","replace":"あなたの幸せを願って","active":true,"filterlinks":false},{"name":"warabe9","source":"^warabe9$","flags":"g","replace":"贈ります","active":true,"filterlinks":false},{"name":"warabe10","source":"^warabe10$","flags":"g","replace":"お祝いの言葉を","active":true,"filterlinks":false},{"name":"gehenna","source":"^生きていたくないよ$","flags":"g","replace":"<p class=\"gehenna\">生きていたくないよ</p><span class=\"gehennamoji\">不　　</span><span class=\"gehennamoji\">適　　</span><span class=\"gehennamoji\">切　　</span><span class=\"gehennamoji\">な　　</span><span class=\"gehennamoji\">発　　</span><span class=\"gehennamoji\">言　　</span><span class=\"gehennamoji\">で　　</span><span class=\"gehennamoji\">す</span>","active":true,"filterlinks":false},{"name":"nijiiro","source":"^N\\!([\\w\\-]+(?:\\d+_)?\\d{3}[\\w\\-]*)$","flags":"g","replace":"<span class=\"nijiiro\"> \\1 </span>","active":true,"filterlinks":false},{"name":"lagtrain","source":"\\[lag\\]\\s?(\\S*(?:\\s+\\S+)*)","flags":"g","replace":"<span class=\"lagtrain\"><span><span> \\1 </span></span></span>","active":true,"filterlinks":false},{"name":"筋肉","source":"^k1$","flags":"g","replace":"<span class=\"muscle\">筋肉</span>","active":true,"filterlinks":false},{"name":"その筋肉","source":"^k2$","flags":"g","replace":"<span class=\"muscle\">その筋肉</span>","active":true,"filterlinks":false},{"name":"kin","source":"^kin$","flags":"g","replace":"<span class=\"muscle-container\"><span class=\"muscle\">その筋肉</span><span class=\"muscle\">筋肉</span><span class=\"muscle\">その筋肉</span><span class=\"muscle\">その筋肉</span><span class=\"muscle\">筋肉</span><span class=\"muscle\">その筋肉</span></span>","active":true,"filterlinks":false},{"name":"jump","source":"\\[jump\\]\\s?(\\S*(?:\\s+\\S+)*)","flags":"g","replace":"<span class=\"haneru\"> \\1 </marquee>","active":true,"filterlinks":false},{"name":"sakasama","source":"\\[saka\\]\\s?(\\S*(?:\\s+\\S+)*)","flags":"g","replace":"<span class=\"sakasama\"> \\1 </span>","active":true,"filterlinks":false},{"name":"ねぇよ","source":"^kinniku$","flags":"g","replace":"<span class=\"kin6\"><span class=\"muscle\">その筋肉</span></span><span class=\"kin5\"><span class=\"muscle\">筋肉</span></span><span class=\"kin4\"><span class=\"muscle\">その筋肉</span></span><span class=\"kin3\"><span class=\"muscle\">その筋肉</span></span><span class=\"kin2\"><span class=\"muscle\">筋肉</span></span><span class=\"kin1\"><span class=\"muscle\">その筋肉</span></span>","active":true,"filterlinks":false}]
